Workbook
Name Slicer_Category: #N/A
Name Slicer_City: #N/A

Sheet Raw Data
A1: OrderID | B1: OrderDate | C1: CustomerName | D1: City | E1: ProductID | F1: ProductName | G1: Category | H1: SalesAmount | I1: Quantity | J1: Cost | K1: PaymentMethod | L1: Salesperson | M1: Profit | N1: SalesCategory | O1: Month
A2: 2001 | B2: 2025-03-01 | C2: Ahmad | D2: Amman | E2: P001 | F2: Mouse | G2: Electronics | H2: 24 | I2: 2 | J2: 16 | K2: Cash | L2: Lina | M2: =H2-J2 -> 8 | N2: =IF(H2>50,"High","Low") -> Low | O2: =TEXT(B2,"mmm yyyy") -> Mar 2025
A3: 2002 | B3: 2025-03-02 | C3: Sara | D3: Zarqa | E3: P002 | F3: Keyboard | G3: Electronics | H3: 20 | I3: 1 | J3: 12 | K3: Card | L3: Omar | M3: =H3-J3 -> 8 | N3: =IF(H3>50,"High","Low") -> Low | O3: =TEXT(B3,"mmm yyyy") -> Mar 2025
A4: 2003 | B4: 2025-03-03 | C4: Ali | D4: Irbid | E4: P003 | F4: Notebook | G4: Stationery | H4: 9 | I4: 3 | J4: 3 | K4: Cash | L4: Lina | M4: =H4-J4 -> 6 | N4: =IF(H4>50,"High","Low") -> Low | O4: =TEXT(B4,"mmm yyyy") -> Mar 2025
A5: 2004 | B5: 2025-03-05 | C5: Rana | D5: Amman | E5: P004 | F5: Pen Set | G5: Stationery | H5: 10 | I5: 2 | J5: 4 | K5: Card | L5: Omar | M5: =H5-J5 -> 6 | N5: =IF(H5>50,"High","Low") -> Low | O5: =TEXT(B5,"mmm yyyy") -> Mar 2025
A6: 2005 | B6: 45722 | C6: Khaled | D6: Aqaba | E6: P005 | F6: Water Bottle | G6: Accessories | H6: 20 | I6: 2 | J6: 8 | K6: Cash | L6: Lina | M6: =H6-J6 -> 12 | N6: =IF(H6>50,"High","Low") -> Low | O6: =TEXT(B6,"mmm yyyy") -> Mar 2025
A7: 2006 | B7: 2025-03-08 | C7: Maha | D7: Amman | E7: P006 | F7: Backpack | G7: Accessories | H7: 50 | I7: 2 | J7: 30 | K7: Card | L7: Omar | M7: =H7-J7 -> 20 | N7: =IF(H7>50,"High","Low") -> Low | O7: =TEXT(B7,"mmm yyyy") -> Mar 2025
A8: 2007 | B8: 2025-03-10 | C8: Yousef | D8: Zarqa | E8: P007 | F8: Headphones | G8: Electronics | H8: 60 | I8: 2 | J8: 40 | K8: Cash | L8: Lina | M8: =H8-J8 -> 20 | N8: =IF(H8>50,"High","Low") -> High | O8: =TEXT(B8,"mmm yyyy") -> Mar 2025
A9: 2008 | B9: 2025-03-12 | C9: Nour | D9: Irbid | E9: P008 | F9: Desk Lamp | G9: Furniture | H9: 18 | I9: 1 | J9: 10 | K9: Card | L9: Omar | M9: =H9-J9 -> 8 | N9: =IF(H9>50,"High","Low") -> Low | O9: =TEXT(B9,"mmm yyyy") -> Mar 2025
A10: 2009 | B10: 2025-03-15 | C10: Huda | D10: Amman | E10: P009 | F10: Office Chair | G10: Furniture | H10: 90 | I10: 1 | J10: 60 | K10: Cash | L10: Lina | M10: =H10-J10 -> 30 | N10: =IF(H10>50,"High","Low") -> High | O10: =TEXT(B10,"mmm yyyy") -> Mar 2025
A11: 2010 | B11: 2025-03-18 | C11: Omar | D11: Aqaba | E11: P010 | F11: Monitor | G11: Electronics | H11: 150 | I11: 1 | J11: 110 | K11: Card | L11: Omar | M11: =H11-J11 -> 40 | N11: =IF(H11>50,"High","Low") -> High | O11: =TEXT(B11,"mmm yyyy") -> Mar 2025
A12: 2011 | B12: 2025-03-20 | C12: Ahmad | D12: Amman | E12: P002 | F12: Keyboard | G12: Electronics | H12: 40 | I12: 2 | J12: 24 | K12: Cash | L12: Lina | M12: =H12-J12 -> 16 | N12: =IF(H12>50,"High","Low") -> Low | O12: =TEXT(B12,"mmm yyyy") -> Mar 2025
A13: 2012 | B13: 2025-03-22 | C13: Sara | D13: Zarqa | E13: P003 | F13: Notebook | G13: Stationery | H13: 6 | I13: 2 | J13: 2 | K13: Card | L13: Omar | M13: =H13-J13 -> 4 | N13: =IF(H13>50,"High","Low") -> Low | O13: =TEXT(B13,"mmm yyyy") -> Mar 2025

Sheet Pivot 1
A3: Row Labels | B3: Sum of SalesAmount
A4: Accessories | B4: 70
A5: Electronics | B5: 294
A6: Furniture | B6: 108
A7: Stationery | B7: 25
A8: Grand Total | B8: 497

Sheet Pivot 2
A3: Row Labels | B3: Sum of SalesAmount
A4: Amman | B4: 214
A5: Aqaba | B5: 170
A6: Irbid | B6: 27
A7: Zarqa | B7: 86
A8: Grand Total | B8: 497

Sheet Pivot 3
A3: Row Labels | B3: Sum of SalesAmount
A4: Lina | B4: 243
A5: Omar | B5: 254
A6: Grand Total | B6: 497

Sheet Pivot 4
A3: Row Labels | B3: Sum of SalesAmount
A4: Mar 2025 | B4: 497
A5: Grand Total | B5: 497

Sheet Dashboard
A1: KPI | B1: Value
A2: Total Sales | B2: =SUM('Raw Data'!H:H) -> 497
A3: Total Profit | B3: =SUM('Raw Data'!M:M) -> 178
A4: Average Sales | B4: =AVERAGE('Raw Data'!H:H) -> 41.416667
A5: Max Sale | B5: =MAX('Raw Data'!H:H) -> 150
A6: Min Sale | B6: =MIN('Raw Data'!H:H) -> 6

Sheet Summary
A1: Best Category: Electronics | B1: Recommendations
A2: Top City: Amman | B2: Focus on Electronics products
A3: Top Salesperson: Omar | B3: Improve low-performing categories
A4: Average Sales: 41.42 | B4: Expand business in Amman
A5: Lowest Sales Category: Stationery | B5: Analyze top salesperson performance
B6: Use dashboard for decision making
